CHANGES.txt
CONTRIBUTORS.txt
COPYRIGHT.txt
LICENSE.txt
MANIFEST.in
README.txt
setup.cfg
setup.py
collective/__init__.py
collective.groupspace.content.egg-info/PKG-INFO
collective.groupspace.content.egg-info/SOURCES.txt
collective.groupspace.content.egg-info/dependency_links.txt
collective.groupspace.content.egg-info/entry_points.txt
collective.groupspace.content.egg-info/namespace_packages.txt
collective.groupspace.content.egg-info/not-zip-safe
collective.groupspace.content.egg-info/paster_plugins.txt
collective.groupspace.content.egg-info/requires.txt
collective.groupspace.content.egg-info/top_level.txt
collective/groupspace/__init__.py
collective/groupspace/content/README.txt
collective/groupspace/content/__init__.py
collective/groupspace/content/config.py
collective/groupspace/content/configure.zcml
collective/groupspace/content/permissions.py
collective/groupspace/content/browser/__init__.py
collective/groupspace/content/browser/configure.zcml
collective/groupspace/content/content/__init__.py
collective/groupspace/content/content/configure.zcml
collective/groupspace/content/content/groupspace.py
collective/groupspace/content/interfaces/__init__.py
collective/groupspace/content/interfaces/groupspace.py
collective/groupspace/content/locales/collective.groupspace.pot
collective/groupspace/content/locales/fr/LC_MESSAGES/collective.groupspace.po
collective/groupspace/content/profiles/default/factorytool.xml
collective/groupspace/content/profiles/default/metadata.xml
collective/groupspace/content/profiles/default/propertiestool.xml
collective/groupspace/content/profiles/default/rolemap.xml
collective/groupspace/content/profiles/default/types.xml
collective/groupspace/content/profiles/default/types/GroupSpace.xml
collective/groupspace/content/tests/__init__.py
collective/groupspace/content/tests/base.py
collective/groupspace/content/tests/test___init__.py
collective/groupspace/content/tests/test_doctest.py
collective/groupspace/content/tests/test_install.py