Metadata-Version: 1.0
Name: collective.groupspace.content
Version: 1.0.2
Summary: Plone collective.groupspace content type for privately working in groups
Home-page: http://plone.org/products/collective.groupspace.content
Author: Maik Roeder
Author-email: roeder@berg.net
License: GPL
Keywords: groupspace,roles,pas,borg.localrole,grufspaces
Platform: UNKNOWN
Classifier: Development Status :: 5 - Production/Stable
Classifier: Environment :: Web Environment
Classifier: Framework :: Plone
Classifier: Framework :: Zope2
Classifier: Intended Audience :: Developers
Classifier: License :: OSI Approved :: GNU General Public License (GPL)
Classifier: Operating System :: OS Independent
Classifier: Programming Language :: Python
Classifier: Topic :: Internet :: WWW/HTTP :: Dynamic Content
Classifier: Topic :: Office/Business :: Groupware
Classifier: Topic :: Software Development :: Libraries :: Python Modules
